requests_llnw_auth.py
requests_llnw_auth-1.0.1.dist-info/LICENSE
requests_llnw_auth-1.0.1.dist-info/METADATA
requests_llnw_auth-1.0.1.dist-info/WHEEL
requests_llnw_auth-1.0.1.dist-info/top_level.txt
requests_llnw_auth-1.0.1.dist-info/RECORD
