Metadata-Version: 2.1
Name: requests-llnw-auth
Version: 1.0.1
Summary: LLNW header-based auth plugin for Python Requests
Home-page: https://github.com/llnw/requests-llnw-auth
Author: Limelight Networks
Author-email: opensource@llnw.com
License: Apache License 2.0
Platform: UNKNOWN
Requires-Python: >=3.6
Requires-Dist: requests (>=2.22.0)
